{
  "page_image": "2015.280761.Kurukh-Orao_text_page-0108.jpg",
  "page_label": "104",
  "status": "extracted",
  "entries": [
    {
      "kurukh_word": "K̲h̲arkharnā",
      "kurukh_word_ascii": "Kharkharna",
      "english_definition": "kan, an, to sweep.",
      "hindi_definition": "बुहारना, झाड़ू लगाना।",
      "part_of_speech": "verb",
      "verb_class": "kan-an",
      "notes": ""
    },
    {
      "kurukh_word": "K̲h̲arrā",
      "kurukh_word_ascii": "Kharra",
      "english_definition": "sprout ; especially fresh bamboo shoots.",
      "hindi_definition": "अंकुर; विशेष रूप से ताज़े बाँस की कोंपलें।",
      "part_of_speech": "noun",
      "notes": ""
    },
    {
      "kurukh_word": "K̲h̲arrā",
      "kurukh_word_ascii": "Kharra",
      "english_definition": "the sign of the plural for the word child, k̲h̲add-k̲h̲arrā offspring.",
      "hindi_definition": "बच्चा शब्द के बहुवचन का चिह्न, k̲h̲add-k̲h̲arrā = संतान।",
      "part_of_speech": "noun",
      "notes": "2nd homograph of K̲h̲arrā — plural sign/offspring"
    },
    {
      "kurukh_word": "K̲h̲arnā",
      "kurukh_word_ascii": "Kharna",
      "english_definition": "to steal.",
      "hindi_definition": "चोरी करना।",
      "part_of_speech": "verb",
      "notes": ""
    },
    {
      "kurukh_word": "K̲h̲ārnā",
      "kurukh_word_ascii": "Kharna",
      "english_definition": "kan, yan, to despise.",
      "hindi_definition": "तिरस्कार करना, तुच्छ समझना।",
      "part_of_speech": "verb",
      "verb_class": "kan-yan",
      "notes": ""
    },
    {
      "kurukh_word": "K̲h̲ārnā",
      "kurukh_word_ascii": "Kharna",
      "english_definition": "kan, yan, to make a course for the flowing off of the water.",
      "hindi_definition": "पानी बहने के लिए नाली या मार्ग बनाना।",
      "part_of_speech": "verb",
      "verb_class": "kan-yan",
      "notes": "2nd homograph of K̲h̲ārnā — make a watercourse"
    },
    {
      "kurukh_word": "K̲h̲ārnā",
      "kurukh_word_ascii": "Kharna",
      "english_definition": "kan, yan, to bite off with the teeth.",
      "hindi_definition": "दांतों से काटना (टुकड़ा काटना)।",
      "part_of_speech": "verb",
      "verb_class": "kan-yan",
      "notes": "3rd homograph of K̲h̲ārnā — bite off"
    },
    {
      "kurukh_word": "K̲h̲assā",
      "kurukh_word_ascii": "Khassa",
      "english_definition": "rope made of hemp.",
      "hindi_definition": "सन की रस्सी।",
      "part_of_speech": "noun",
      "notes": ""
    },
    {
      "kurukh_word": "K̲h̲asnā",
      "kurukh_word_ascii": "Khasna",
      "english_definition": "kan, yan, to anoint to smear with oil.",
      "hindi_definition": "तेल लगाना, तेल मलना (मालिश करना)।",
      "part_of_speech": "verb",
      "verb_class": "kan-yan",
      "notes": ""
    },
    {
      "kurukh_word": "K̲h̲asrā",
      "kurukh_word_ascii": "Khasra",
      "english_definition": "itches.",
      "hindi_definition": "खुजली, खाज।",
      "part_of_speech": "noun",
      "notes": ""
    },
    {
      "kurukh_word": "K̲h̲assnā",
      "kurukh_word_ascii": "Khassna",
      "english_definition": "kan, yan, to benumb, to chloroform.",
      "hindi_definition": "सुन्न करना, बेहोश करना (क्लोरोफॉर्म देना)।",
      "part_of_speech": "verb",
      "verb_class": "kan-yan",
      "notes": ""
    },
    {
      "kurukh_word": "K̲h̲aṭarṇā",
      "kurukh_word_ascii": "Khatarna",
      "english_definition": "kan, an, to distribute, dispense.",
      "hindi_definition": "बाँटना, वितरण करना।",
      "part_of_speech": "verb",
      "verb_class": "kan-an",
      "notes": ""
    },
    {
      "kurukh_word": "K̲h̲aṭarnakrnā",
      "kurukh_word_ascii": "Khatarnakrna",
      "english_definition": "kan, an, to dole out among themselves.",
      "hindi_definition": "आपस में बाँटना।",
      "part_of_speech": "verb",
      "verb_class": "kan-an",
      "notes": ""
    },
    {
      "kurukh_word": "K̲h̲aṭnā",
      "kurukh_word_ascii": "Khatna",
      "english_definition": "ckan, c'an, to boil.",
      "hindi_definition": "उबालना (सकर्मक)।",
      "part_of_speech": "verb",
      "verb_class": "ckan-c'an",
      "notes": ""
    },
    {
      "kurukh_word": "K̲h̲aṭṭnā",
      "kurukh_word_ascii": "Khattna",
      "english_definition": "kan, yan, to distribute, to portion out.",
      "hindi_definition": "बाँटना, हिस्सा लगाना।",
      "part_of_speech": "verb",
      "verb_class": "kan-yan",
      "notes": ""
    },
    {
      "kurukh_word": "K̲h̲aṭṭnā ittnā",
      "kurukh_word_ascii": "Khattna ittna",
      "english_definition": "to exchange eatables.",
      "hindi_definition": "खाद्य पदार्थों का आदान-प्रदान करना।",
      "part_of_speech": "verb phrase",
      "notes": ""
    },
    {
      "kurukh_word": "K̲h̲aṭṭī",
      "kurukh_word_ascii": "Khatti",
      "english_definition": "wretched, unhappy woman.",
      "hindi_definition": "अभागी, दुखी स्त्री।",
      "part_of_speech": "noun",
      "notes": ""
    },
    {
      "kurukh_word": "K̲h̲attas",
      "kurukh_word_ascii": "Khattas",
      "english_definition": "a wretched fellow.",
      "hindi_definition": "अभागा या दुखी पुरुष/व्यक्ति।",
      "part_of_speech": "noun",
      "notes": ""
    },
    {
      "kurukh_word": "K̲h̲aũkhnā",
      "kurukh_word_ascii": "Khaunkhna",
      "english_definition": "kan, yan, to make a hole in wood.",
      "hindi_definition": "लकड़ी में छेद करना।",
      "part_of_speech": "verb",
      "verb_class": "kan-yan",
      "notes": ""
    },
    {
      "kurukh_word": "K̲h̲āynā",
      "kurukh_word_ascii": "Khayna",
      "english_definition": "kan, yan, to dry, intr.",
      "hindi_definition": "सूखना (अकर्मक)।",
      "part_of_speech": "verb",
      "verb_class": "kan-yan",
      "notes": ""
    },
    {
      "kurukh_word": "K̲h̲āyk̲h̲āyrnā",
      "kurukh_word_ascii": "Khaykhayrna",
      "english_definition": "to have a dry mouth from thirst.",
      "hindi_definition": "प्यास से मुँह सूखना।",
      "part_of_speech": "verb",
      "notes": ""
    },
    {
      "kurukh_word": "K̲h̲āyk̲h̲āyrā lagnā",
      "kurukh_word_ascii": "Khaykhayra lagna",
      "english_definition": "to be thirsty.",
      "hindi_definition": "प्यास लगना।",
      "part_of_speech": "verb phrase",
      "notes": ""
    },
    {
      "kurukh_word": "K̲h̲āydnā",
      "kurukh_word_ascii": "Khaydna",
      "english_definition": "kan, an, to dry, trans.",
      "hindi_definition": "सुखाना (सकर्मक)।",
      "part_of_speech": "verb",
      "verb_class": "kan-an",
      "notes": ""
    },
    {
      "kurukh_word": "K̲h̲āydkā ghāsī",
      "kurukh_word_ascii": "Khaydka ghasi",
      "english_definition": "hay.",
      "hindi_definition": "सूखी घास, पुआल।",
      "part_of_speech": "noun",
      "notes": ""
    },
    {
      "kurukh_word": "K̲h̲ebdā",
      "kurukh_word_ascii": "Khebda",
      "english_definition": "ear.",
      "hindi_definition": "कान।",
      "part_of_speech": "noun",
      "notes": ""
    },
    {
      "kurukh_word": "K̲h̲ebdan ildnā",
      "kurukh_word_ascii": "Khebdan ildna",
      "english_definition": "to listen, to incline to hear.",
      "hindi_definition": "कान लगाकर सुनना, ध्यान से सुनना।",
      "part_of_speech": "verb phrase",
      "notes": ""
    },
    {
      "kurukh_word": "K̲h̲ebdan ūrnā",
      "kurukh_word_ascii": "Khebdan urna",
      "english_definition": "to give secret advice.",
      "hindi_definition": "कान में फूंकना, गुप्त सलाह देना।",
      "part_of_speech": "verb phrase",
      "notes": ""
    },
    {
      "kurukh_word": "K̲h̲ebdā k̲h̲orpnā",
      "kurukh_word_ascii": "Khebda khorpna",
      "english_definition": "to have an inflamed or sore ear.",
      "hindi_definition": "कान बहना, कान में सूजन या घाव होना।",
      "part_of_speech": "verb phrase",
      "notes": ""
    },
    {
      "kurukh_word": "K̲h̲ebdā uṭṭnā",
      "kurukh_word_ascii": "Khebda uttna",
      "english_definition": "to shut one's ear, to take no heed of.",
      "hindi_definition": "कान बंद कर लेना, अनसुना करना।",
      "part_of_speech": "verb phrase",
      "notes": ""
    },
    {
      "kurukh_word": "K̲h̲edd",
      "kurukh_word_ascii": "Khedd",
      "english_definition": "foot.",
      "hindi_definition": "पैर, पैर का पंजा।",
      "part_of_speech": "noun",
      "notes": ""
    },
    {
      "kurukh_word": "K̲h̲edd cappō",
      "kurukh_word_ascii": "Khedd cappo",
      "english_definition": "south, forenoon.",
      "hindi_definition": "दक्षिण दिशा, दोपहर से पहले का समय।",
      "part_of_speech": "noun",
      "notes": ""
    },
    {
      "kurukh_word": "K̲h̲edd jālā",
      "kurukh_word_ascii": "Khedd jala",
      "english_definition": "purple colored.",
      "hindi_definition": "बैंगनी रंग का।",
      "part_of_speech": "adjective",
      "notes": ""
    },
    {
      "kurukh_word": "K̲h̲edd nōrhnā",
      "kurukh_word_ascii": "Khedd norhna",
      "english_definition": "to become engaged ; the ceremony, i.e. feetwashing done by the girl to her future husband as a ratification of her betrothal.",
      "hindi_definition": "सगाई होना; पैर धोने की रस्म जो लड़की अपने होने वाले पति के लिए सगाई की पुष्टि के रूप में करती है।",
      "part_of_speech": "verb phrase",
      "notes": ""
    }
  ]
}
